imbib.py
imbib-0.1.0.dist-info/entry_points.txt
imbib-0.1.0.dist-info/WHEEL
imbib-0.1.0.dist-info/METADATA
imbib-0.1.0.dist-info/RECORD
