Metadata-Version: 1.2
Name: imbib
Version: 0.1.0
Summary: Cite papers by their URLs.
Home-page: http://github.com/sampsyo/imbib
License: UNKNOWN
Author: Adrian Sampson
Author-email: adrian@radbox.org
Requires-Python: 3
Requires-Dist: click (>=6.2)
Requires-Dist: beautifulsoup4 (>=4.0.0)
Requires-Dist: pybtex (>=0.20.1)
Requires-Dist: requests (>=2.9.1)
